ernie4us/__init__.py
ernie4us/modeling.py
ernie4us/tokenization.py
ernie4us-0.2.0.dist-info/LICENSE
ernie4us-0.2.0.dist-info/METADATA
ernie4us-0.2.0.dist-info/WHEEL
ernie4us-0.2.0.dist-info/top_level.txt
ernie4us-0.2.0.dist-info/zip-safe
ernie4us-0.2.0.dist-info/RECORD
