Metadata-Version: 2.1
Name: ernie4us
Version: 0.2.0
Summary: Tensorflow accessible helper for Baidu's ERNIE NLP model
Home-page: https://github.com/hotpads/ERNIE-for-the-rest-of-us/
Author: Winston Quock
License: Apache License 2.0
Platform: UNKNOWN
Classifier: Programming Language :: Python :: 3
Requires-Dist: tensorflow (>=2.0)
Requires-Dist: dataclasses
